{
  "clazz" : "org.gradoop.model.impl.EPGraphTest",
  "methods" : [ {
    "method" : "testExcludeWithOverlappingGraphs",
    "datacollectorResults" : [ {
      "name" : "de.dagere.kopeme.datacollection.TimeDataCollectorNoGC",
      "chunks" : [ ],
      "results" : [ {
        "value" : 2.68259568484E10,
        "deviation" : 0.025319085344676973,
        "min" : 2.4905056624E10,
        "max" : 2.7128002156E10,
        "warmup" : 0,
        "iterations" : 10,
        "repetitions" : 2,
        "commit" : null,
        "vmRunConfiguration" : {
          "showStart" : false,
          "executeBeforeClassInMeasurement" : false,
          "redirectToTemp" : false,
          "redirectToNull" : true,
          "useKieker" : false
        },
        "javaVersion" : "1.8.0_362",
        "cpu" : "model name : Intel(R) Core(TM) i7-4770 CPU @ 3.40GHz",
        "memory" : "MemTotal: 16280544 kB",
        "date" : 1685796908363,
        "fulldata" : {
          "fileName" : null,
          "values" : [ {
            "startTime" : 1685796640009,
            "value" : 24905056624
          }, {
            "startTime" : 1685796664914,
            "value" : 27081050697
          }, {
            "startTime" : 1685796691995,
            "value" : 27022087654
          }, {
            "startTime" : 1685796719017,
            "value" : 27089109915
          }, {
            "startTime" : 1685796746106,
            "value" : 27093452561
          }, {
            "startTime" : 1685796773200,
            "value" : 26870663490
          }, {
            "startTime" : 1685796800070,
            "value" : 27128002156
          }, {
            "startTime" : 1685796827199,
            "value" : 27023981998
          }, {
            "startTime" : 1685796854223,
            "value" : 26961607060
          }, {
            "startTime" : 1685796881184,
            "value" : 27084556329
          } ]
        }
      } ]
    } ]
  } ]
}