{
  "clazz" : "org.gradoop.flink.io.impl.csv.CSVDataSinkTest",
  "methods" : [ {
    "method" : "testWriteExtendedProperties",
    "datacollectorResults" : [ {
      "name" : "de.dagere.kopeme.datacollection.TimeDataCollectorNoGC",
      "chunks" : [ ],
      "results" : [ {
        "value" : 2.6844619587E10,
        "deviation" : 0.07886400358412919,
        "min" : 2.4876442627E10,
        "max" : 3.2334362456E10,
        "warmup" : 0,
        "iterations" : 10,
        "repetitions" : 64,
        "commit" : null,
        "vmRunConfiguration" : {
          "showStart" : false,
          "executeBeforeClassInMeasurement" : false,
          "redirectToTemp" : false,
          "redirectToNull" : true,
          "useKieker" : false
        },
        "javaVersion" : "1.8.0_362",
        "cpu" : "model name : Intel(R) Core(TM) i7-4770 CPU @ 3.40GHz",
        "memory" : "MemTotal: 16280544 kB",
        "date" : 1681243612100,
        "fulldata" : {
          "fileName" : null,
          "values" : [ {
            "startTime" : 1681243343280,
            "value" : 32334362456
          }, {
            "startTime" : 1681243375615,
            "value" : 25722899641
          }, {
            "startTime" : 1681243401338,
            "value" : 24876442627
          }, {
            "startTime" : 1681243426214,
            "value" : 25762542515
          }, {
            "startTime" : 1681243451977,
            "value" : 25599446153
          }, {
            "startTime" : 1681243477576,
            "value" : 25826263757
          }, {
            "startTime" : 1681243503403,
            "value" : 26772241201
          }, {
            "startTime" : 1681243530175,
            "value" : 26704939889
          }, {
            "startTime" : 1681243556880,
            "value" : 26868840832
          }, {
            "startTime" : 1681243583749,
            "value" : 27978216799
          } ]
        }
      } ]
    } ]
  } ]
}