{
  "clazz" : "org.gradoop.io.writer.JsonWriterTest",
  "methods" : [ {
    "method" : "writerTest",
    "datacollectorResults" : [ {
      "name" : "de.dagere.kopeme.datacollection.TimeDataCollectorNoGC",
      "chunks" : [ ],
      "results" : [ {
        "value" : 3956809.4000000004,
        "deviation" : 1.4335793703369166,
        "min" : 1623765.0,
        "max" : 2.0071616E7,
        "warmup" : 0,
        "iterations" : 10,
        "repetitions" : 2,
        "commit" : null,
        "vmRunConfiguration" : {
          "showStart" : false,
          "executeBeforeClassInMeasurement" : false,
          "redirectToTemp" : false,
          "redirectToNull" : true,
          "useKieker" : false
        },
        "javaVersion" : "1.8.0_362",
        "cpu" : "model name : Intel(R) Core(TM) i7-4770 CPU @ 3.40GHz",
        "memory" : "MemTotal: 16280544 kB",
        "date" : 1682975695708,
        "fulldata" : {
          "fileName" : null,
          "values" : [ {
            "startTime" : 1682975695569,
            "value" : 20071616
          }, {
            "startTime" : 1682975695589,
            "value" : 2071186
          }, {
            "startTime" : 1682975695592,
            "value" : 2710866
          }, {
            "startTime" : 1682975695594,
            "value" : 1937919
          }, {
            "startTime" : 1682975695596,
            "value" : 2516792
          }, {
            "startTime" : 1682975695599,
            "value" : 2318680
          }, {
            "startTime" : 1682975695601,
            "value" : 2035814
          }, {
            "startTime" : 1682975695603,
            "value" : 2478017
          }, {
            "startTime" : 1682975695606,
            "value" : 1803439
          }, {
            "startTime" : 1682975695608,
            "value" : 1623765
          } ]
        }
      } ]
    } ]
  } ]
}