{
  "clazz" : "org.gradoop.flink.io.impl.csv.CSVDataSinkTest",
  "methods" : [ {
    "method" : "testWriteExtendedProperties",
    "datacollectorResults" : [ {
      "name" : "de.dagere.kopeme.datacollection.TimeDataCollectorNoGC",
      "chunks" : [ ],
      "results" : [ {
        "value" : 9.2563578555E9,
        "deviation" : 0.23016187641018196,
        "min" : 7.619131683E9,
        "max" : 1.465366784E10,
        "warmup" : 0,
        "iterations" : 10,
        "repetitions" : 12,
        "commit" : null,
        "vmRunConfiguration" : {
          "showStart" : false,
          "executeBeforeClassInMeasurement" : false,
          "redirectToTemp" : false,
          "redirectToNull" : true,
          "useKieker" : false
        },
        "javaVersion" : "1.8.0_362",
        "cpu" : "model name : Intel(R) Core(TM) i7-4770 CPU @ 3.40GHz",
        "memory" : "MemTotal: 16280544 kB",
        "date" : 1679271228318,
        "fulldata" : {
          "fileName" : null,
          "values" : [ {
            "startTime" : 1679271135495,
            "value" : 14653667840
          }, {
            "startTime" : 1679271150149,
            "value" : 10371036216
          }, {
            "startTime" : 1679271160520,
            "value" : 10284195453
          }, {
            "startTime" : 1679271170805,
            "value" : 9117862016
          }, {
            "startTime" : 1679271179923,
            "value" : 7936920997
          }, {
            "startTime" : 1679271187860,
            "value" : 8146376087
          }, {
            "startTime" : 1679271196006,
            "value" : 8234889721
          }, {
            "startTime" : 1679271204241,
            "value" : 8218711564
          }, {
            "startTime" : 1679271212460,
            "value" : 7980786978
          }, {
            "startTime" : 1679271220440,
            "value" : 7619131683
          } ]
        }
      } ]
    } ]
  } ]
}