{
  "clazz" : "org.gradoop.common.model.impl.properties.PropertyValueTest",
  "methods" : [ {
    "method" : "testListValueMaxSize",
    "datacollectorResults" : [ {
      "name" : "de.dagere.kopeme.datacollection.TimeDataCollectorNoGC",
      "chunks" : [ ],
      "results" : [ {
        "value" : 1.5004429245E9,
        "deviation" : 0.37703391000061853,
        "min" : 1.302536827E9,
        "max" : 3.11024355E9,
        "warmup" : 0,
        "iterations" : 10,
        "repetitions" : 8000,
        "commit" : null,
        "vmRunConfiguration" : {
          "showStart" : false,
          "executeBeforeClassInMeasurement" : false,
          "redirectToTemp" : false,
          "redirectToNull" : true,
          "useKieker" : false
        },
        "javaVersion" : "1.8.0_362",
        "cpu" : "model name : Intel(R) Core(TM) i7-4770 CPU @ 3.40GHz",
        "memory" : "MemTotal: 16280544 kB",
        "date" : 1679186387331,
        "fulldata" : {
          "fileName" : null,
          "values" : [ {
            "startTime" : 1679186372243,
            "value" : 3110243550
          }, {
            "startTime" : 1679186375354,
            "value" : 1338728023
          }, {
            "startTime" : 1679186376693,
            "value" : 1331796951
          }, {
            "startTime" : 1679186378024,
            "value" : 1313555892
          }, {
            "startTime" : 1679186379338,
            "value" : 1328804782
          }, {
            "startTime" : 1679186380667,
            "value" : 1314704408
          }, {
            "startTime" : 1679186381982,
            "value" : 1319449355
          }, {
            "startTime" : 1679186383301,
            "value" : 1321321933
          }, {
            "startTime" : 1679186384622,
            "value" : 1323287524
          }, {
            "startTime" : 1679186385946,
            "value" : 1302536827
          } ]
        }
      } ]
    } ]
  } ]
}