{
  "clazz" : "org.gradoop.model.impl.LogicalGraphGetterTest",
  "methods" : [ {
    "method" : "testIncomingEdges2",
    "datacollectorResults" : [ {
      "name" : "de.dagere.kopeme.datacollection.TimeDataCollectorNoGC",
      "chunks" : [ ],
      "results" : [ {
        "value" : 1.0225855410000001E8,
        "deviation" : 1.6194414487675362,
        "min" : 3.1861917E7,
        "max" : 5.71968732E8,
        "warmup" : 0,
        "iterations" : 10,
        "repetitions" : 2,
        "commit" : null,
        "vmRunConfiguration" : {
          "showStart" : false,
          "executeBeforeClassInMeasurement" : false,
          "redirectToTemp" : false,
          "redirectToNull" : true,
          "useKieker" : false
        },
        "parameters" : {
          "JUNIT_PARAMETERIZED" : "Execution mode = CLUSTER"
        },
        "javaVersion" : "1.8.0_362",
        "cpu" : "model name : Intel(R) Core(TM) i7-4770 CPU @ 3.40GHz",
        "memory" : "MemTotal: 16280544 kB",
        "date" : 1680986453352,
        "fulldata" : {
          "fileName" : null,
          "values" : [ {
            "startTime" : 1680986452099,
            "value" : 571968732
          }, {
            "startTime" : 1680986452671,
            "value" : 63155108
          }, {
            "startTime" : 1680986452734,
            "value" : 56173692
          }, {
            "startTime" : 1680986452790,
            "value" : 48130576
          }, {
            "startTime" : 1680986452838,
            "value" : 44253710
          }, {
            "startTime" : 1680986452883,
            "value" : 80136709
          }, {
            "startTime" : 1680986452963,
            "value" : 31861917
          }, {
            "startTime" : 1680986452995,
            "value" : 44554033
          }, {
            "startTime" : 1680986453039,
            "value" : 42467611
          }, {
            "startTime" : 1680986453082,
            "value" : 39883453
          } ]
        }
      } ]
    } ]
  } ]
}