{
  "clazz" : "org.gradoop.common.model.impl.pojo.VertexTest",
  "methods" : [ {
    "method" : "createVertexPojoTest",
    "datacollectorResults" : [ {
      "name" : "de.dagere.kopeme.datacollection.TimeDataCollectorNoGC",
      "chunks" : [ ],
      "results" : [ {
        "value" : 6.476863374E8,
        "deviation" : 0.1545726730835656,
        "min" : 5.99061534E8,
        "max" : 9.25838124E8,
        "warmup" : 0,
        "iterations" : 10,
        "repetitions" : 1000000,
        "commit" : null,
        "vmRunConfiguration" : {
          "showStart" : false,
          "executeBeforeClassInMeasurement" : false,
          "redirectToTemp" : false,
          "redirectToNull" : true,
          "useKieker" : false
        },
        "javaVersion" : "1.8.0_362",
        "cpu" : "model name : Intel(R) Core(TM) i7-4770 CPU @ 3.40GHz",
        "memory" : "MemTotal: 16280544 kB",
        "date" : 1679171570245,
        "fulldata" : {
          "fileName" : null,
          "values" : [ {
            "startTime" : 1679171563677,
            "value" : 925838124
          }, {
            "startTime" : 1679171564603,
            "value" : 609515950
          }, {
            "startTime" : 1679171565212,
            "value" : 609529378
          }, {
            "startTime" : 1679171565822,
            "value" : 624177932
          }, {
            "startTime" : 1679171566446,
            "value" : 610729327
          }, {
            "startTime" : 1679171567057,
            "value" : 618275172
          }, {
            "startTime" : 1679171567675,
            "value" : 600659530
          }, {
            "startTime" : 1679171568276,
            "value" : 599061534
          }, {
            "startTime" : 1679171568875,
            "value" : 604660522
          }, {
            "startTime" : 1679171569480,
            "value" : 674415905
          } ]
        }
      } ]
    } ]
  } ]
}