{
  "clazz" : "org.gradoop.temporal.model.impl.operators.aggregation.functions.AverageDurationTest",
  "methods" : [ {
    "method" : "testWithAggregation",
    "datacollectorResults" : [ {
      "name" : "de.dagere.kopeme.datacollection.TimeDataCollectorNoGC",
      "chunks" : [ ],
      "results" : [ {
        "value" : 6.589405645E8,
        "deviation" : 0.7393342380455068,
        "min" : 2.77029854E8,
        "max" : 1.921302311E9,
        "warmup" : 0,
        "iterations" : 10,
        "repetitions" : 12,
        "commit" : null,
        "vmRunConfiguration" : {
          "showStart" : false,
          "executeBeforeClassInMeasurement" : false,
          "redirectToTemp" : false,
          "redirectToNull" : true,
          "useKieker" : false
        },
        "javaVersion" : "1.8.0_362",
        "cpu" : "model name : Intel(R) Core(TM) i7-4770 CPU @ 3.40GHz",
        "memory" : "MemTotal: 16280544 kB",
        "date" : 1678702789594,
        "fulldata" : {
          "fileName" : null,
          "values" : [ {
            "startTime" : 1678702782814,
            "value" : 1921302311
          }, {
            "startTime" : 1678702784735,
            "value" : 919213806
          }, {
            "startTime" : 1678702785654,
            "value" : 537222997
          }, {
            "startTime" : 1678702786192,
            "value" : 676802351
          }, {
            "startTime" : 1678702786868,
            "value" : 672743328
          }, {
            "startTime" : 1678702787541,
            "value" : 558898832
          }, {
            "startTime" : 1678702788100,
            "value" : 348434144
          }, {
            "startTime" : 1678702788449,
            "value" : 372749604
          }, {
            "startTime" : 1678702788821,
            "value" : 305008418
          }, {
            "startTime" : 1678702789126,
            "value" : 277029854
          } ]
        }
      } ]
    } ]
  } ]
}