{
  "clazz" : "org.gradoop.storage.hbase.HBaseGraphStoreTest",
  "methods" : [ {
    "method" : "propertyTypeTest",
    "datacollectorResults" : [ {
      "name" : "de.dagere.kopeme.datacollection.TimeDataCollectorNoGC",
      "chunks" : [ ],
      "results" : [ {
        "value" : 2.44675502836E11,
        "deviation" : 2.379668256151792,
        "min" : 3.7097890175E10,
        "max" : 1.685660285384E12,
        "warmup" : 0,
        "iterations" : 6,
        "repetitions" : 12,
        "commit" : null,
        "vmRunConfiguration" : {
          "showStart" : false,
          "executeBeforeClassInMeasurement" : false,
          "redirectToTemp" : false,
          "redirectToNull" : true,
          "useKieker" : false
        },
        "javaVersion" : "1.8.0_362",
        "cpu" : "model name : Intel(R) Core(TM) i7-4770 CPU @ 3.40GHz",
        "memory" : "MemTotal: 16280544 kB",
        "date" : 1685660313777,
        "error" : true,
        "fulldata" : {
          "fileName" : null,
          "values" : [ {
            "startTime" : 1685660013639,
            "value" : 37097890175
          }, {
            "startTime" : 1685660050738,
            "value" : 38383839707
          }, {
            "startTime" : 1685660089121,
            "value" : 38617198890
          }, {
            "startTime" : 1685660127739,
            "value" : 39100812217
          }, {
            "startTime" : 1685660166839,
            "value" : 40475021506
          }, {
            "startTime" : 1685660207314,
            "value" : 39018137175
          }, {
            "startTime" : 1685660246333,
            "value" : 39050837634
          }, {
            "startTime" : 1685660285384,
            "value" : 1685660285384
          } ]
        }
      } ]
    } ]
  } ]
}