{
  "clazz" : "org.gradoop.model.impl.LogicalGraphAggregateTest",
  "methods" : [ {
    "method" : "aggregateEdgeCountTest",
    "datacollectorResults" : [ {
      "name" : "de.dagere.kopeme.datacollection.TimeDataCollectorNoGC",
      "chunks" : [ ],
      "results" : [ {
        "value" : 3.8108346005E9,
        "deviation" : 0.17871253702510978,
        "min" : 2.394699165E9,
        "max" : 4.581963653E9,
        "warmup" : 0,
        "iterations" : 10,
        "repetitions" : 2,
        "commit" : null,
        "vmRunConfiguration" : {
          "showStart" : false,
          "executeBeforeClassInMeasurement" : false,
          "redirectToTemp" : false,
          "redirectToNull" : true,
          "useKieker" : false
        },
        "javaVersion" : "1.8.0_362",
        "cpu" : "model name : Intel(R) Core(TM) i7-4770 CPU @ 3.40GHz",
        "memory" : "MemTotal: 16280544 kB",
        "date" : 1680968154952,
        "fulldata" : {
          "fileName" : null,
          "values" : [ {
            "startTime" : 1680968116718,
            "value" : 4581963653
          }, {
            "startTime" : 1680968121300,
            "value" : 2749175654
          }, {
            "startTime" : 1680968124050,
            "value" : 2394699165
          }, {
            "startTime" : 1680968126444,
            "value" : 4140405299
          }, {
            "startTime" : 1680968130585,
            "value" : 4061373535
          }, {
            "startTime" : 1680968134646,
            "value" : 4094427289
          }, {
            "startTime" : 1680968138741,
            "value" : 4126870778
          }, {
            "startTime" : 1680968142868,
            "value" : 3943769963
          }, {
            "startTime" : 1680968146811,
            "value" : 4018110116
          }, {
            "startTime" : 1680968150830,
            "value" : 3997550553
          } ]
        }
      } ]
    } ]
  } ]
}