{
  "clazz" : "org.gradoop.model.impl.LogicalGraphGetterTest",
  "methods" : [ {
    "method" : "testGetEdges",
    "datacollectorResults" : [ {
      "name" : "de.dagere.kopeme.datacollection.TimeDataCollectorNoGC",
      "chunks" : [ ],
      "results" : [ {
        "value" : 1.5512228279999998E8,
        "deviation" : 1.0468978566177833,
        "min" : 6.9499592E7,
        "max" : 6.1141143E8,
        "warmup" : 0,
        "iterations" : 10,
        "repetitions" : 2,
        "commit" : null,
        "vmRunConfiguration" : {
          "showStart" : false,
          "executeBeforeClassInMeasurement" : false,
          "redirectToTemp" : false,
          "redirectToNull" : true,
          "useKieker" : false
        },
        "parameters" : {
          "JUNIT_PARAMETERIZED" : "Execution mode = CLUSTER"
        },
        "javaVersion" : "1.8.0_362",
        "cpu" : "model name : Intel(R) Core(TM) i7-4770 CPU @ 3.40GHz",
        "memory" : "MemTotal: 16280544 kB",
        "date" : 1680982410342,
        "fulldata" : {
          "fileName" : null,
          "values" : [ {
            "startTime" : 1680982408571,
            "value" : 611411430
          }, {
            "startTime" : 1680982409183,
            "value" : 138067760
          }, {
            "startTime" : 1680982409321,
            "value" : 135331149
          }, {
            "startTime" : 1680982409456,
            "value" : 109058972
          }, {
            "startTime" : 1680982409565,
            "value" : 127761575
          }, {
            "startTime" : 1680982409693,
            "value" : 105799073
          }, {
            "startTime" : 1680982409799,
            "value" : 70694944
          }, {
            "startTime" : 1680982409870,
            "value" : 110389621
          }, {
            "startTime" : 1680982409980,
            "value" : 69499592
          }, {
            "startTime" : 1680982410050,
            "value" : 73208712
          } ]
        }
      } ]
    } ]
  } ]
}