{
  "clazz" : "org.gradoop.model.impl.DefaultGraphTest",
  "methods" : [ {
    "method" : "createDefaultGraphTest",
    "datacollectorResults" : [ {
      "name" : "de.dagere.kopeme.datacollection.TimeDataCollectorNoGC",
      "chunks" : [ ],
      "results" : [ {
        "value" : 991880.2999999999,
        "deviation" : 2.9060310800430798,
        "min" : 33412.0,
        "max" : 9187549.0,
        "warmup" : 0,
        "iterations" : 10,
        "repetitions" : 2,
        "commit" : null,
        "vmRunConfiguration" : {
          "showStart" : false,
          "executeBeforeClassInMeasurement" : false,
          "redirectToTemp" : false,
          "redirectToNull" : true,
          "useKieker" : false
        },
        "javaVersion" : "1.8.0_362",
        "cpu" : "model name : Intel(R) Core(TM) i7-4770 CPU @ 3.40GHz",
        "memory" : "MemTotal: 16280544 kB",
        "date" : 1682967018324,
        "fulldata" : {
          "fileName" : null,
          "values" : [ {
            "startTime" : 1682967018234,
            "value" : 9187549
          }, {
            "startTime" : 1682967018243,
            "value" : 41266
          }, {
            "startTime" : 1682967018243,
            "value" : 35117
          }, {
            "startTime" : 1682967018243,
            "value" : 34504
          }, {
            "startTime" : 1682967018243,
            "value" : 33932
          }, {
            "startTime" : 1682967018243,
            "value" : 38772
          }, {
            "startTime" : 1682967018243,
            "value" : 34403
          }, {
            "startTime" : 1682967018244,
            "value" : 438523
          }, {
            "startTime" : 1682967018244,
            "value" : 41325
          }, {
            "startTime" : 1682967018244,
            "value" : 33412
          } ]
        }
      } ]
    } ]
  } ]
}