{
  "measurementConfig" : {
    "vms" : 30,
    "earlyStop" : false,
    "warmup" : 5,
    "iterations" : 5,
    "repetitions" : 2,
    "logFullData" : true,
    "useGC" : false,
    "callSyncBetweenVMs" : true,
    "waitTimeBetweenVMs" : 1000,
    "maxLogSizeInMb" : 100,
    "kiekerConfig" : {
      "useKieker" : true,
      "useSourceInstrumentation" : true,
      "useSelectiveInstrumentation" : true,
      "useAggregation" : true,
      "useCircularQueue" : false,
      "enableAdaptiveMonitoring" : false,
      "adaptiveInstrumentation" : false,
      "kiekerAggregationInterval" : 5000,
      "record" : "DURATION",
      "onlyOneCallRecording" : false,
      "extractMethod" : false,
      "traceSizeInMb" : 100,
      "kiekerQueueSize" : 10000000,
      "createDefaultConstructor" : true,
      "kiekerWaitTime" : 5,
      "excludeForTracing" : [ "new org.eclipse.jetty.logging.JettyLevel.<init>(..)", "* org.eclipse.jetty.logging.JettyLevel.*(..)", "*[] org.eclipse.jetty.logging.JettyLevel.*(..)", "*.* org.eclipse.jetty.logging.JettyLevel.*(..)", "*.*.* org.eclipse.jetty.logging.JettyLevel.*(..)", "*.*.*.* org.eclipse.jetty.logging.JettyLevel.*(..)", "*.*.*.*.* org.eclipse.jetty.logging.JettyLevel.*(..)", "new org.eclipse.jetty.logging.JettyLoggerConfiguration.<init>(..)", "* org.eclipse.jetty.logging.JettyLoggerConfiguration.*(..)", "*[] org.eclipse.jetty.logging.JettyLoggerConfiguration.*(..)", "*.* org.eclipse.jetty.logging.JettyLoggerConfiguration.*(..)", "*.*.* org.eclipse.jetty.logging.JettyLoggerConfiguration.*(..)", "*.*.*.* org.eclipse.jetty.logging.JettyLoggerConfiguration.*(..)", "*.*.*.*.* org.eclipse.jetty.logging.JettyLoggerConfiguration.*(..)", "new org.eclipse.jetty.logging.JettyLoggingServiceProvider.<init>(..)", "* org.eclipse.jetty.logging.JettyLoggingServiceProvider.*(..)", "*[] org.eclipse.jetty.logging.JettyLoggingServiceProvider.*(..)", "*.* org.eclipse.jetty.logging.JettyLoggingServiceProvider.*(..)", "*.*.* org.eclipse.jetty.logging.JettyLoggingServiceProvider.*(..)", "*.*.*.* org.eclipse.jetty.logging.JettyLoggingServiceProvider.*(..)", "*.*.*.*.* org.eclipse.jetty.logging.JettyLoggingServiceProvider.*(..)", "new org.eclipse.jetty.logging.JettyLoggerFactory.<init>(..)", "* org.eclipse.jetty.logging.JettyLoggerFactory.*(..)", "*[] org.eclipse.jetty.logging.JettyLoggerFactory.*(..)", "*.* org.eclipse.jetty.logging.JettyLoggerFactory.*(..)", "*.*.* org.eclipse.jetty.logging.JettyLoggerFactory.*(..)", "*.*.*.* org.eclipse.jetty.logging.JettyLoggerFactory.*(..)", "*.*.*.*.* org.eclipse.jetty.logging.JettyLoggerFactory.*(..)", "new org.eclipse.jetty.logging.StdErrAppender.<init>(..)", "* org.eclipse.jetty.logging.StdErrAppender.*(..)", "*[] org.eclipse.jetty.logging.StdErrAppender.*(..)", "*.* org.eclipse.jetty.logging.StdErrAppender.*(..)", "*.*.* org.eclipse.jetty.logging.StdErrAppender.*(..)", "*.*.*.* org.eclipse.jetty.logging.StdErrAppender.*(..)", "*.*.*.*.* org.eclipse.jetty.logging.StdErrAppender.*(..)", "new org.eclipse.jetty.logging.Timestamp.<init>(..)", "* org.eclipse.jetty.logging.Timestamp.*(..)", "*[] org.eclipse.jetty.logging.Timestamp.*(..)", "*.* org.eclipse.jetty.logging.Timestamp.*(..)", "*.*.* org.eclipse.jetty.logging.Timestamp.*(..)", "*.*.*.* org.eclipse.jetty.logging.Timestamp.*(..)", "*.*.*.*.* org.eclipse.jetty.logging.Timestamp.*(..)", "new org.eclipse.jetty.logging.Timestamp$Tick.<init>(..)", "* org.eclipse.jetty.logging.Timestamp$Tick.*(..)", "*[] org.eclipse.jetty.logging.Timestamp$Tick.*(..)", "*.* org.eclipse.jetty.logging.Timestamp$Tick.*(..)", "*.*.* org.eclipse.jetty.logging.Timestamp$Tick.*(..)", "*.*.*.* org.eclipse.jetty.logging.Timestamp$Tick.*(..)", "*.*.*.*.* org.eclipse.jetty.logging.Timestamp$Tick.*(..)", "new org.eclipse.jetty.logging.JettyLogger.<init>(..)", "* org.eclipse.jetty.logging.JettyLogger.*(..)", "*[] org.eclipse.jetty.logging.JettyLogger.*(..)", "*.* org.eclipse.jetty.logging.JettyLogger.*(..)", "*.*.* org.eclipse.jetty.logging.JettyLogger.*(..)", "*.*.*.* org.eclipse.jetty.logging.JettyLogger.*(..)", "*.*.*.*.* org.eclipse.jetty.logging.JettyLogger.*(..)" ]
    },
    "saveAll" : true,
    "javaVersion" : "1.8.0_352",
    "measurementStrategy" : "PARALLEL",
    "statisticsConfig" : {
      "type1error" : 0.2,
      "type2error" : 0.1,
      "outlierFactor" : 3.29,
      "statisticTest" : "T_TEST"
    },
    "executionConfig" : {
      "timeout" : 300000,
      "redirectSubprocessOutputToFile" : true,
      "useTieredCompilation" : false,
      "removeSnapshots" : false,
      "useAlternativeBuildfile" : false,
      "excludeLog4jSlf4jImpl" : false,
      "excludeLog4jToSlf4j" : false,
      "executeBeforeClassInMeasurement" : false,
      "onlyMeasureWorkload" : false,
      "showStart" : false,
      "redirectToNull" : true,
      "createDetailDebugFiles" : true
    },
    "fixedCommitConfig" : {
      "commit" : "937394435a5e1430d025a1d7cc9f47224ea805b0",
      "commitOld" : "d916ecc90a9a75ba35470bd137a48b944570ba8b"
    }
  },
  "causeConfig" : {
    "splitAggregated" : true,
    "minTime" : 0.1,
    "ignoreEOIs" : true,
    "rcaStrategy" : "UNTIL_SOURCE_CHANGE",
    "levels" : 1,
    "testCase" : {
      "clazz" : "org.gradoop.model.impl.DefaultVertexTest",
      "method" : "createWithIDTest",
      "module" : "gradoop-core",
      "params" : null
    },
    "propertyFolder" : "/home/abrik/peass/results/properties_gradoop"
  },
  "nodes" : {
    "call" : "org.gradoop.model.impl.DefaultVertexTest#createWithIDTest",
    "kiekerPattern" : "public void org.gradoop.model.impl.DefaultVertexTest.createWithIDTest()",
    "otherKiekerPattern" : "public void org.gradoop.model.impl.DefaultVertexTest.createWithIDTest()",
    "module" : "gradoop-core",
    "statistic" : {
      "meanOld" : 726399.7137931035,
      "meanCurrent" : 690424.4241379312,
      "deviationOld" : 152050.9654655629,
      "deviationCurrent" : 184957.5859498655,
      "vms" : 29,
      "callsOld" : 150,
      "calls" : 150,
      "tvalue" : 0.8091273006010715
    },
    "childs" : [ {
      "call" : "org.gradoop.model.impl.VertexFactory#createDefaultVertexWithID",
      "kiekerPattern" : "public static org.gradoop.model.Vertex org.gradoop.model.impl.VertexFactory.createDefaultVertexWithID(java.lang.Long)",
      "otherKiekerPattern" : "public static org.gradoop.model.Vertex org.gradoop.model.impl.VertexFactory.createDefaultVertexWithID(java.lang.Long)",
      "module" : "gradoop-core",
      "statistic" : {
        "meanOld" : 387860.40344827593,
        "meanCurrent" : 341906.0392857142,
        "deviationOld" : 105203.55933976785,
        "deviationCurrent" : 61399.73561103856,
        "vms" : 28,
        "callsOld" : 150,
        "calls" : 150,
        "tvalue" : 2.0224634316408587
      },
      "childs" : [ {
        "call" : "org.gradoop.model.impl.VertexFactory#createDefaultVertex",
        "kiekerPattern" : "public static org.gradoop.model.Vertex org.gradoop.model.impl.VertexFactory.createDefaultVertex(java.lang.Long,java.lang.Iterable,java.util.Map,java.lang.Iterable,java.lang.Iterable,java.lang.Iterable)",
        "otherKiekerPattern" : "public static org.gradoop.model.Vertex org.gradoop.model.impl.VertexFactory.createDefaultVertex(java.lang.Long,java.lang.String,java.util.Map,java.lang.Iterable,java.lang.Iterable,java.lang.Iterable)",
        "module" : "gradoop-core",
        "statistic" : {
          "meanOld" : 351432.78620689653,
          "meanCurrent" : 319629.0099999999,
          "deviationOld" : 65844.50239672212,
          "deviationCurrent" : 52146.45970938965,
          "vms" : 29,
          "callsOld" : 150,
          "calls" : 150,
          "tvalue" : 2.052319053972361
        },
        "childs" : [ ]
      } ]
    }, {
      "call" : "org.gradoop.model.impl.MultiLabeledPropertyContainer#getID",
      "kiekerPattern" : "public java.lang.Long org.gradoop.model.impl.MultiLabeledPropertyContainer.getID()",
      "otherKiekerPattern" : "public java.lang.Long org.gradoop.model.impl.LabeledPropertyContainer.getID()",
      "module" : "gradoop-core",
      "statistic" : {
        "meanOld" : 623.42,
        "meanCurrent" : 587.6466666666668,
        "deviationOld" : 99.95145511352173,
        "deviationCurrent" : 104.6759094681699,
        "vms" : 30,
        "callsOld" : 150,
        "calls" : 150,
        "tvalue" : 1.3538034044554017
      },
      "childs" : [ ]
    }, {
      "call" : "org.gradoop.model.impl.MultiLabeledPropertyContainer#getLabelCount",
      "kiekerPattern" : "public int org.gradoop.model.impl.MultiLabeledPropertyContainer.getLabelCount()",
      "otherKiekerPattern" : "ADDED",
      "module" : "gradoop-core",
      "statistic" : {
        "meanOld" : "NaN",
        "meanCurrent" : "NaN",
        "deviationOld" : "NaN",
        "deviationCurrent" : "NaN",
        "vms" : 0,
        "callsOld" : 0,
        "calls" : 0,
        "tvalue" : -1.0,
        "change" : true
      },
      "childs" : [ ]
    } ]
  }
}