{
  "clazz" : "org.gradoop.flink.model.impl.operators.aggregation.AggregationTest",
  "methods" : [ {
    "method" : "testGraphUnsupportedPropertyValueType",
    "datacollectorResults" : [ {
      "name" : "de.dagere.kopeme.datacollection.TimeDataCollectorNoGC",
      "chunks" : [ ],
      "results" : [ {
        "value" : 2.7647784758600002E10,
        "deviation" : 0.15683089674979353,
        "min" : 2.1346118703E10,
        "max" : 3.3916452747E10,
        "warmup" : 0,
        "iterations" : 10,
        "repetitions" : 1600,
        "commit" : null,
        "vmRunConfiguration" : {
          "showStart" : false,
          "executeBeforeClassInMeasurement" : false,
          "redirectToTemp" : false,
          "redirectToNull" : true,
          "useKieker" : false
        },
        "javaVersion" : "1.8.0_362",
        "cpu" : "model name : Intel(R) Core(TM) i7-4770 CPU @ 3.40GHz",
        "memory" : "MemTotal: 16280544 kB",
        "date" : 1678657000150,
        "fulldata" : {
          "fileName" : null,
          "values" : [ {
            "startTime" : 1678656723028,
            "value" : 33916452747
          }, {
            "startTime" : 1678656756945,
            "value" : 26007519492
          }, {
            "startTime" : 1678656782953,
            "value" : 29507733480
          }, {
            "startTime" : 1678656812460,
            "value" : 31766853329
          }, {
            "startTime" : 1678656844227,
            "value" : 21570291543
          }, {
            "startTime" : 1678656865798,
            "value" : 25497303245
          }, {
            "startTime" : 1678656891295,
            "value" : 30178996866
          }, {
            "startTime" : 1678656921474,
            "value" : 31355877776
          }, {
            "startTime" : 1678656952830,
            "value" : 21346118703
          }, {
            "startTime" : 1678656974176,
            "value" : 25330700405
          } ]
        }
      } ]
    } ]
  } ]
}