{
  "clazz" : "gradoop-examples§csv.io.reader.CSVReaderTest",
  "methods" : [ {
    "method" : "checkEdgeCSVInputTest",
    "datacollectorResults" : [ {
      "name" : "de.dagere.kopeme.datacollection.TimeDataCollectorNoGC",
      "chunks" : [ {
        "chunkStartTime" : 1685681999379,
        "results" : [ {
          "value" : 1.685682009011E12,
          "deviation" : 0.0,
          "min" : 1.685682009011E12,
          "max" : 1.685682009011E12,
          "warmup" : 0,
          "iterations" : 1,
          "repetitions" : 1000000,
          "commit" : "c19474960ad3fe63005f3e981cd4bb289aef0217",
          "vmRunConfiguration" : { },
          "date" : 1685682009107
        }, {
          "value" : 1.685682332672E12,
          "deviation" : 0.0,
          "min" : 1.685682332672E12,
          "max" : 1.685682332672E12,
          "warmup" : 0,
          "iterations" : 1,
          "repetitions" : 200000,
          "commit" : "c19474960ad3fe63005f3e981cd4bb289aef0217",
          "vmRunConfiguration" : { },
          "date" : 1685682332775
        }, {
          "value" : 1.685682656023E12,
          "deviation" : 0.0,
          "min" : 1.685682656023E12,
          "max" : 1.685682656023E12,
          "warmup" : 0,
          "iterations" : 1,
          "repetitions" : 40000,
          "commit" : "c19474960ad3fe63005f3e981cd4bb289aef0217",
          "vmRunConfiguration" : { },
          "date" : 1685682656125
        }, {
          "value" : 1.685682979359E12,
          "deviation" : 0.0,
          "min" : 1.685682979359E12,
          "max" : 1.685682979359E12,
          "warmup" : 0,
          "iterations" : 1,
          "repetitions" : 8000,
          "commit" : "c19474960ad3fe63005f3e981cd4bb289aef0217",
          "vmRunConfiguration" : { },
          "date" : 1685682979459
        }, {
          "value" : 8.433126037299999E9,
          "deviation" : 4.7763673707439774E8,
          "min" : 8.211303206E9,
          "max" : 9.784661365E9,
          "warmup" : 0,
          "iterations" : 10,
          "repetitions" : 8000,
          "commit" : "7bff26f3cbb07a4da2cbfe66713be568f3547622",
          "vmRunConfiguration" : { },
          "date" : 1685683072502
        }, {
          "value" : 1.685683083378E12,
          "deviation" : 0.0,
          "min" : 1.685683083378E12,
          "max" : 1.685683083378E12,
          "warmup" : 0,
          "iterations" : 1,
          "repetitions" : 1600,
          "commit" : "c19474960ad3fe63005f3e981cd4bb289aef0217",
          "vmRunConfiguration" : { },
          "date" : 1685683083481
        }, {
          "value" : 1.8091373436999998E9,
          "deviation" : 2.773645146387031E8,
          "min" : 1.66545785E9,
          "max" : 2.581536947E9,
          "warmup" : 0,
          "iterations" : 10,
          "repetitions" : 1600,
          "commit" : "7bff26f3cbb07a4da2cbfe66713be568f3547622",
          "vmRunConfiguration" : { },
          "date" : 1685683110533
        }, {
          "value" : 1.685683120896E12,
          "deviation" : 0.0,
          "min" : 1.685683120896E12,
          "max" : 1.685683120896E12,
          "warmup" : 0,
          "iterations" : 1,
          "repetitions" : 320,
          "commit" : "c19474960ad3fe63005f3e981cd4bb289aef0217",
          "vmRunConfiguration" : { },
          "date" : 1685683120993
        }, {
          "value" : 4.450371859E8,
          "deviation" : 1.4805851908961582E8,
          "min" : 3.51856847E8,
          "max" : 8.53181773E8,
          "warmup" : 0,
          "iterations" : 10,
          "repetitions" : 320,
          "commit" : "7bff26f3cbb07a4da2cbfe66713be568f3547622",
          "vmRunConfiguration" : { },
          "date" : 1685683134354
        }, {
          "value" : 1.685683145011E12,
          "deviation" : 0.0,
          "min" : 1.685683145011E12,
          "max" : 1.685683145011E12,
          "warmup" : 0,
          "iterations" : 1,
          "repetitions" : 64,
          "commit" : "c19474960ad3fe63005f3e981cd4bb289aef0217",
          "vmRunConfiguration" : { },
          "date" : 1685683145108
        }, {
          "value" : 1.3077688550000001E8,
          "deviation" : 6.224247636366786E7,
          "min" : 8.4150562E7,
          "max" : 2.84602317E8,
          "warmup" : 0,
          "iterations" : 10,
          "repetitions" : 64,
          "commit" : "7bff26f3cbb07a4da2cbfe66713be568f3547622",
          "vmRunConfiguration" : { },
          "date" : 1685683155418
        }, {
          "value" : 1.685683165578E12,
          "deviation" : 0.0,
          "min" : 1.685683165578E12,
          "max" : 1.685683165578E12,
          "warmup" : 0,
          "iterations" : 1,
          "repetitions" : 12,
          "commit" : "c19474960ad3fe63005f3e981cd4bb289aef0217",
          "vmRunConfiguration" : { },
          "date" : 1685683165675
        }, {
          "value" : 4.3664570599999994E7,
          "deviation" : 2.9178607296478588E7,
          "min" : 2.4953138E7,
          "max" : 1.23458136E8,
          "warmup" : 0,
          "iterations" : 10,
          "repetitions" : 12,
          "commit" : "7bff26f3cbb07a4da2cbfe66713be568f3547622",
          "vmRunConfiguration" : { },
          "date" : 1685683175392
        }, {
          "value" : 1.685683185945E12,
          "deviation" : 0.0,
          "min" : 1.685683185945E12,
          "max" : 1.685683185945E12,
          "warmup" : 0,
          "iterations" : 1,
          "repetitions" : 2,
          "commit" : "c19474960ad3fe63005f3e981cd4bb289aef0217",
          "vmRunConfiguration" : { },
          "date" : 1685683186041
        }, {
          "value" : 1.6367708399999999E7,
          "deviation" : 1.8451886337784916E7,
          "min" : 6371926.0,
          "max" : 6.7015293E7,
          "warmup" : 0,
          "iterations" : 10,
          "repetitions" : 2,
          "commit" : "7bff26f3cbb07a4da2cbfe66713be568f3547622",
          "vmRunConfiguration" : { },
          "date" : 1685683194819
        } ]
      } ],
      "results" : [ ]
    } ]
  } ]
}