{
  "clazz" : "org.gradoop.flink.model.impl.functions.filters.CombinableFilterTest",
  "methods" : [ {
    "method" : "testWithGraph",
    "datacollectorResults" : [ {
      "name" : "de.dagere.kopeme.datacollection.TimeDataCollectorNoGC",
      "chunks" : [ ],
      "results" : [ {
        "value" : 3.9439140748999996E9,
        "deviation" : 0.27407754372942256,
        "min" : 2.914850782E9,
        "max" : 6.689492462E9,
        "warmup" : 0,
        "iterations" : 10,
        "repetitions" : 12,
        "commit" : null,
        "vmRunConfiguration" : {
          "showStart" : false,
          "executeBeforeClassInMeasurement" : false,
          "redirectToTemp" : false,
          "redirectToNull" : true,
          "useKieker" : false
        },
        "javaVersion" : "1.8.0_362",
        "cpu" : "model name : Intel(R) Core(TM) i7-4770 CPU @ 3.40GHz",
        "memory" : "MemTotal: 16280544 kB",
        "date" : 1679267868856,
        "fulldata" : {
          "fileName" : null,
          "values" : [ {
            "startTime" : 1679267829238,
            "value" : 6689492462
          }, {
            "startTime" : 1679267835927,
            "value" : 4229153784
          }, {
            "startTime" : 1679267840156,
            "value" : 3590123103
          }, {
            "startTime" : 1679267843747,
            "value" : 3621327981
          }, {
            "startTime" : 1679267847368,
            "value" : 4003625098
          }, {
            "startTime" : 1679267851372,
            "value" : 4281763270
          }, {
            "startTime" : 1679267855653,
            "value" : 3161790099
          }, {
            "startTime" : 1679267858815,
            "value" : 3006552168
          }, {
            "startTime" : 1679267861822,
            "value" : 2914850782
          }, {
            "startTime" : 1679267864737,
            "value" : 3940462002
          } ]
        }
      } ]
    } ]
  } ]
}